[
  {
    "node": {
      "description": "Scripts I created during IPWSP-NE (Introducing Python and Web Services Programmability for Network Engineers v3.0) training course and kept for posterity",
      "name": "IPWSP-NE",
      "releases": {
        "nodes": [
          {
            "name": "Initial Release"
          }
        ]
      },
      "updatedAt": "2018-01-31T23:43:32Z",
      "url": "https://github.com/loudsquelch/IPWSP-NE"
    }
  },
  {
    "node": {
      "description": "Website content",
      "name": "www.loudsquel.ch",
      "releases": {
        "nodes": []
      },
      "updatedAt": "2018-02-01T22:49:06Z",
      "url": "https://github.com/loudsquelch/www.loudsquel.ch"
    }
  }
]